{"timestamp": "2026-01-31T00:27:00.570439", "data": {"ticker": "MGM", "quarterly_revenue": [{"period": "Sep 2024", "date": "2024-09-30", "value": 4183138000.0, "formatted": "$4.18B"}, {"period": "Dec 2024", "date": "2024-12-31", "value": 4346562000.0, "formatted": "$4.35B"}, {"period": "Mar 2025", "date": "2025-03-31", "value": 4277082000.0, "formatted": "$4.28B"}, {"period": "Jun 2025", "date": "2025-06-30", "value": 4404870000.0, "formatted": "$4.40B"}, {"period": "Sep 2025", "date": "2025-09-30", "value": 4250464000.0, "formatted": "$4.25B"}], "quarterly_earnings": [{"period": "Sep 2024", "date": "2024-09-30", "value": 184578000.0, "formatted": "$184.58M"}, {"period": "Dec 2024", "date": "2024-12-31", "value": 157432000.0, "formatted": "$157.43M"}, {"period": "Mar 2025", "date": "2025-03-31", "value": 148554000.0, "formatted": "$148.55M"}, {"period": "Jun 2025", "date": "2025-06-30", "value": 48951000.0, "formatted": "$48.95M"}, {"period": "Sep 2025", "date": "2025-09-30", "value": -285255000.0, "formatted": "$-285.25M"}], "annual_revenue": [{"period": "FY 2021", "date": "2021-12-31", "value": 9680140000.0, "formatted": "$9.68B"}, {"period": "FY 2022", "date": "2022-12-31", "value": 13127485000.0, "formatted": "$13.13B"}, {"period": "FY 2023", "date": "2023-12-31", "value": 16164249000.0, "formatted": "$16.16B"}, {"period": "FY 2024", "date": "2024-12-31", "value": 17240545000.0, "formatted": "$17.24B"}], "annual_earnings": [{"period": "FY 2021", "date": "2021-12-31", "value": 1254370000.0, "formatted": "$1.25B"}, {"period": "FY 2022", "date": "2022-12-31", "value": 1473093000.0, "formatted": "$1.47B"}, {"period": "FY 2023", "date": "2023-12-31", "value": 1142180000.0, "formatted": "$1.14B"}, {"period": "FY 2024", "date": "2024-12-31", "value": 746558000.0, "formatted": "$746.56M"}]}}