{"timestamp": "2026-01-31T16:50:38.280071", "data": {"ticker": "PSKY", "period": "5y", "count": 1256, "week_52_high": 20.86, "week_52_low": 9.95, "data": [{"date": "2021-02-01", "close": 46.53, "volume": 18855000}, {"date": "2021-02-02", "close": 44.69, "volume": 17683400}, {"date": "2021-02-03", "close": 46.29, "volume": 13200000}, {"date": "2021-02-04", "close": 46.29, "volume": 18711000}, {"date": "2021-02-05", "close": 48.05, "volume": 15575300}, {"date": "2021-02-08", "close": 48.46, "volume": 16656200}, {"date": "2021-02-09", "close": 48.93, "volume": 7948500}, {"date": "2021-02-10", "close": 50.3, "volume": 13028200}, {"date": "2021-02-11", "close": 50.86, "volume": 8545700}, {"date": "2021-02-12", "close": 51.84, "volume": 11056500}, {"date": "2021-02-16", "close": 52.58, "volume": 14584500}, {"date": "2021-02-17", "close": 54.24, "volume": 10102800}, {"date": "2021-02-18", "close": 55.26, "volume": 14245100}, {"date": "2021-02-19", "close": 55.74, "volume": 14426600}, {"date": "2021-02-22", "close": 58.81, "volume": 21760600}, {"date": "2021-02-23", "close": 57.23, "volume": 18354800}, {"date": "2021-02-24", "close": 58.33, "volume": 17322500}, {"date": "2021-02-25", "close": 55.57, "volume": 25151200}, {"date": "2021-02-26", "close": 57.34, "volume": 16360300}, {"date": "2021-03-01", "close": 59.69, "volume": 13425700}, {"date": "2021-03-02", "close": 61.1, "volume": 14417500}, {"date": "2021-03-03", "close": 63.05, "volume": 17460100}, {"date": "2021-03-04", "close": 63.91, "volume": 21489300}, {"date": "2021-03-05", "close": 66.01, "volume": 14159000}, {"date": "2021-03-08", "close": 74.38, "volume": 21341100}, {"date": "2021-03-09", "close": 70.83, "volume": 23611600}, {"date": "2021-03-10", "close": 73.7, "volume": 22506900}, {"date": "2021-03-11", "close": 76.71, "volume": 22371000}, {"date": "2021-03-12", "close": 84.65, "volume": 38020400}, {"date": "2021-03-15", "close": 85.89, "volume": 32035400}, {"date": "2021-03-16", "close": 85.81, "volume": 29110100}, {"date": "2021-03-17", "close": 82.33, "volume": 34687600}, {"date": "2021-03-18", "close": 86.27, "volume": 31797800}, {"date": "2021-03-19", "close": 86.8, "volume": 33518700}, {"date": "2021-03-22", "close": 89.46, "volume": 20400200}, {"date": "2021-03-23", "close": 81.36, "volume": 37782300}, {"date": "2021-03-24", "close": 62.5, "volume": 89815300}, {"date": "2021-03-25", "close": 59.16, "volume": 44269500}, {"date": "2021-03-26", "close": 43.0, "volume": 216631000}, {"date": "2021-03-29", "close": 40.13, "volume": 213578900}, {"date": "2021-03-30", "close": 41.56, "volume": 150842500}, {"date": "2021-03-31", "close": 40.21, "volume": 92028600}, {"date": "2021-04-01", "close": 39.8, "volume": 59501200}, {"date": "2021-04-05", "close": 38.25, "volume": 68076000}, {"date": "2021-04-06", "close": 39.54, "volume": 125164900}, {"date": "2021-04-07", "close": 39.13, "volume": 84665200}, {"date": "2021-04-08", "close": 37.71, "volume": 58371800}, {"date": "2021-04-09", "close": 37.34, "volume": 49660000}, {"date": "2021-04-12", "close": 35.46, "volume": 59418100}, {"date": "2021-04-13", "close": 36.1, "volume": 33145100}, {"date": "2021-04-14", "close": 35.86, "volume": 35659100}, {"date": "2021-04-15", "close": 34.99, "volume": 34635500}, {"date": "2021-04-16", "close": 35.08, "volume": 40042700}, {"date": "2021-04-19", "close": 34.24, "volume": 44779700}, {"date": "2021-04-20", "close": 33.81, "volume": 41652900}, {"date": "2021-04-21", "close": 36.42, "volume": 52142800}, {"date": "2021-04-22", "close": 36.31, "volume": 60658800}, {"date": "2021-04-23", "close": 37.19, "volume": 40878500}, {"date": "2021-04-26", "close": 37.29, "volume": 30501300}, {"date": "2021-04-27", "close": 38.17, "volume": 33759800}, {"date": "2021-04-28", "close": 36.94, "volume": 27913200}, {"date": "2021-04-29", "close": 37.0, "volume": 22505200}, {"date": "2021-04-30", "close": 36.57, "volume": 20587400}, {"date": "2021-05-03", "close": 35.36, "volume": 34064100}, {"date": "2021-05-04", "close": 35.64, "volume": 20480800}, {"date": "2021-05-05", "close": 34.86, "volume": 24750100}, {"date": "2021-05-06", "close": 34.01, "volume": 44431900}, {"date": "2021-05-07", "close": 35.12, "volume": 25483700}, {"date": "2021-05-10", "close": 35.01, "volume": 18927400}, {"date": "2021-05-11", "close": 35.2, "volume": 19701400}, {"date": "2021-05-12", "close": 34.83, "volume": 21179800}, {"date": "2021-05-13", "close": 34.33, "volume": 20742900}, {"date": "2021-05-14", "close": 34.69, "volume": 17029200}, {"date": "2021-05-17", "close": 34.25, "volume": 33202600}, {"date": "2021-05-18", "close": 35.81, "volume": 29181900}, {"date": "2021-05-19", "close": 35.39, "volume": 19409600}, {"date": "2021-05-20", "close": 37.02, "volume": 36244500}, {"date": "2021-05-21", "close": 37.58, "volume": 27099400}, {"date": "2021-05-24", "close": 37.04, "volume": 19473100}, {"date": "2021-05-25", "close": 36.47, "volume": 15314900}, {"date": "2021-05-26", "close": 37.86, "volume": 18656600}, {"date": "2021-05-27", "close": 38.47, "volume": 22191800}, {"date": "2021-05-28", "close": 37.82, "volume": 14547300}, {"date": "2021-06-01", "close": 37.98, "volume": 11165200}, {"date": "2021-06-02", "close": 37.96, "volume": 20988600}, {"date": "2021-06-03", "close": 37.07, "volume": 18451200}, {"date": "2021-06-04", "close": 37.18, "volume": 11105600}, {"date": "2021-06-07", "close": 37.21, "volume": 9004600}, {"date": "2021-06-08", "close": 37.16, "volume": 12402900}, {"date": "2021-06-09", "close": 37.67, "volume": 15497300}, {"date": "2021-06-10", "close": 37.01, "volume": 12086700}, {"date": "2021-06-11", "close": 37.76, "volume": 11266100}, {"date": "2021-06-14", "close": 38.22, "volume": 13862700}, {"date": "2021-06-15", "close": 37.36, "volume": 19307900}, {"date": "2021-06-16", "close": 37.49, "volume": 12538600}, {"date": "2021-06-17", "close": 36.04, "volume": 21893700}, {"date": "2021-06-18", "close": 35.89, "volume": 24690600}, {"date": "2021-06-21", "close": 36.73, "volume": 14021300}, {"date": "2021-06-22", "close": 36.54, "volume": 8517300}, {"date": "2021-06-23", "close": 37.52, "volume": 29032600}, {"date": "2021-06-24", "close": 38.44, "volume": 17000900}, {"date": "2021-06-25", "close": 39.29, "volume": 15530300}, {"date": "2021-06-28", "close": 41.25, "volume": 43425000}, {"date": "2021-06-29", "close": 40.02, "volume": 18654100}, {"date": "2021-06-30", "close": 40.53, "volume": 12847500}, {"date": "2021-07-01", "close": 40.31, "volume": 13624100}, {"date": "2021-07-02", "close": 39.6, "volume": 10022300}, {"date": "2021-07-06", "close": 38.44, "volume": 14026900}, {"date": "2021-07-07", "close": 38.38, "volume": 9848700}, {"date": "2021-07-08", "close": 37.18, "volume": 15650400}, {"date": "2021-07-09", "close": 38.35, "volume": 10049600}, {"date": "2021-07-12", "close": 38.95, "volume": 17104900}, {"date": "2021-07-13", "close": 38.18, "volume": 9441000}, {"date": "2021-07-14", "close": 37.56, "volume": 11243000}, {"date": "2021-07-15", "close": 37.02, "volume": 9672000}, {"date": "2021-07-16", "close": 36.13, "volume": 10837100}, {"date": "2021-07-19", "close": 35.75, "volume": 12677300}, {"date": "2021-07-20", "close": 36.22, "volume": 12779000}, {"date": "2021-07-21", "close": 37.03, "volume": 8950800}, {"date": "2021-07-22", "close": 36.65, "volume": 6260300}, {"date": "2021-07-23", "close": 36.75, "volume": 6552900}, {"date": "2021-07-26", "close": 37.8, "volume": 12283700}, {"date": "2021-07-27", "close": 37.07, "volume": 7622600}, {"date": "2021-07-28", "close": 37.35, "volume": 9449600}, {"date": "2021-07-29", "close": 37.38, "volume": 6833200}, {"date": "2021-07-30", "close": 36.7, "volume": 8020600}, {"date": "2021-08-02", "close": 36.62, "volume": 8873800}, {"date": "2021-08-03", "close": 34.49, "volume": 34007800}, {"date": "2021-08-04", "close": 34.78, "volume": 17040600}, {"date": "2021-08-05", "close": 37.26, "volume": 19426900}, {"date": "2021-08-06", "close": 37.21, "volume": 10609500}, {"date": "2021-08-09", "close": 36.13, "volume": 12343600}, {"date": "2021-08-10", "close": 36.54, "volume": 11877200}, {"date": "2021-08-11", "close": 36.6, "volume": 8285900}, {"date": "2021-08-12", "close": 35.83, "volume": 8250300}, {"date": "2021-08-13", "close": 35.11, "volume": 8991800}, {"date": "2021-08-16", "close": 34.54, "volume": 9775300}, {"date": "2021-08-17", "close": 35.0, "volume": 12938800}, {"date": "2021-08-18", "close": 36.29, "volume": 20720100}, {"date": "2021-08-19", "close": 35.54, "volume": 12395500}, {"date": "2021-08-20", "close": 35.61, "volume": 10167300}, {"date": "2021-08-23", "close": 36.16, "volume": 8201500}, {"date": "2021-08-24", "close": 36.49, "volume": 8818500}, {"date": "2021-08-25", "close": 36.74, "volume": 9384000}, {"date": "2021-08-26", "close": 35.83, "volume": 8032500}, {"date": "2021-08-27", "close": 36.66, "volume": 7827600}, {"date": "2021-08-30", "close": 36.07, "volume": 8721000}, {"date": "2021-08-31", "close": 37.17, "volume": 12153600}, {"date": "2021-09-01", "close": 37.13, "volume": 7088000}, {"date": "2021-09-02", "close": 37.25, "volume": 9273300}, {"date": "2021-09-03", "close": 37.01, "volume": 7396500}, {"date": "2021-09-07", "close": 37.32, "volume": 9260800}, {"date": "2021-09-08", "close": 36.68, "volume": 9544800}, {"date": "2021-09-09", "close": 36.17, "volume": 8952900}, {"date": "2021-09-10", "close": 35.55, "volume": 10474100}, {"date": "2021-09-13", "close": 36.2, "volume": 8894700}, {"date": "2021-09-14", "close": 35.11, "volume": 16633100}, {"date": "2021-09-15", "close": 36.41, "volume": 9786400}, {"date": "2021-09-16", "close": 36.47, "volume": 7633000}, {"date": "2021-09-17", "close": 36.07, "volume": 9895300}, {"date": "2021-09-20", "close": 35.05, "volume": 13967100}, {"date": "2021-09-21", "close": 34.87, "volume": 6875400}, {"date": "2021-09-22", "close": 35.36, "volume": 9331300}, {"date": "2021-09-23", "close": 36.14, "volume": 8066800}, {"date": "2021-09-24", "close": 36.07, "volume": 5406400}, {"date": "2021-09-27", "close": 36.48, "volume": 7119000}, {"date": "2021-09-28", "close": 36.29, "volume": 9474000}, {"date": "2021-09-29", "close": 36.19, "volume": 7628300}, {"date": "2021-09-30", "close": 35.64, "volume": 9657300}, {"date": "2021-10-01", "close": 35.99, "volume": 6887500}, {"date": "2021-10-04", "close": 35.28, "volume": 7925800}, {"date": "2021-10-05", "close": 35.69, "volume": 7714200}, {"date": "2021-10-06", "close": 35.33, "volume": 9146900}, {"date": "2021-10-07", "close": 35.94, "volume": 9246900}, {"date": "2021-10-08", "close": 35.91, "volume": 6541900}, {"date": "2021-10-11", "close": 35.51, "volume": 6762700}, {"date": "2021-10-12", "close": 35.31, "volume": 6081800}, {"date": "2021-10-13", "close": 35.51, "volume": 7715400}, {"date": "2021-10-14", "close": 35.6, "volume": 6305600}, {"date": "2021-10-15", "close": 35.11, "volume": 12981100}, {"date": "2021-10-18", "close": 34.76, "volume": 12958100}, {"date": "2021-10-19", "close": 35.24, "volume": 6645500}, {"date": "2021-10-20", "close": 35.06, "volume": 6878300}, {"date": "2021-10-21", "close": 34.08, "volume": 15778100}, {"date": "2021-10-22", "close": 33.84, "volume": 13533900}, {"date": "2021-10-25", "close": 33.93, "volume": 7760800}, {"date": "2021-10-26", "close": 33.45, "volume": 7146300}, {"date": "2021-10-27", "close": 32.32, "volume": 17112300}, {"date": "2021-10-28", "close": 33.39, "volume": 9769000}, {"date": "2021-10-29", "close": 32.67, "volume": 8460000}, {"date": "2021-11-01", "close": 33.6, "volume": 9750900}, {"date": "2021-11-02", "close": 33.71, "volume": 7792800}, {"date": "2021-11-03", "close": 33.87, "volume": 7745700}, {"date": "2021-11-04", "close": 32.38, "volume": 21669100}, {"date": "2021-11-05", "close": 32.78, "volume": 11927300}, {"date": "2021-11-08", "close": 32.33, "volume": 12223600}, {"date": "2021-11-09", "close": 32.02, "volume": 8759300}, {"date": "2021-11-10", "close": 31.92, "volume": 9085500}, {"date": "2021-11-11", "close": 32.11, "volume": 10585300}, {"date": "2021-11-12", "close": 31.75, "volume": 11691800}, {"date": "2021-11-15", "close": 32.27, "volume": 10887400}, {"date": "2021-11-16", "close": 31.71, "volume": 10061900}, {"date": "2021-11-17", "close": 31.64, "volume": 9241200}, {"date": "2021-11-18", "close": 30.88, "volume": 13599300}, {"date": "2021-11-19", "close": 30.36, "volume": 12878500}, {"date": "2021-11-22", "close": 30.25, "volume": 12943800}, {"date": "2021-11-23", "close": 29.72, "volume": 15514800}, {"date": "2021-11-24", "close": 29.98, "volume": 12147400}, {"date": "2021-11-26", "close": 29.42, "volume": 8737400}, {"date": "2021-11-29", "close": 29.12, "volume": 15881300}, {"date": "2021-11-30", "close": 27.92, "volume": 21862400}, {"date": "2021-12-01", "close": 26.79, "volume": 17249900}, {"date": "2021-12-02", "close": 26.66, "volume": 31862500}, {"date": "2021-12-03", "close": 28.03, "volume": 24840000}, {"date": "2021-12-06", "close": 28.07, "volume": 14798200}, {"date": "2021-12-07", "close": 28.31, "volume": 16599200}, {"date": "2021-12-08", "close": 28.72, "volume": 10991900}, {"date": "2021-12-09", "close": 28.03, "volume": 10748400}, {"date": "2021-12-10", "close": 28.16, "volume": 18471600}, {"date": "2021-12-13", "close": 27.36, "volume": 8300100}, {"date": "2021-12-14", "close": 26.91, "volume": 12239300}, {"date": "2021-12-15", "close": 26.88, "volume": 13234200}, {"date": "2021-12-16", "close": 27.04, "volume": 11798400}, {"date": "2021-12-17", "close": 26.84, "volume": 18207700}, {"date": "2021-12-20", "close": 26.08, "volume": 15714400}, {"date": "2021-12-21", "close": 26.69, "volume": 11746900}, {"date": "2021-12-22", "close": 26.53, "volume": 14243900}, {"date": "2021-12-23", "close": 27.8, "volume": 14137400}, {"date": "2021-12-27", "close": 27.39, "volume": 12801800}, {"date": "2021-12-28", "close": 27.39, "volume": 11393400}, {"date": "2021-12-29", "close": 27.27, "volume": 13096800}, {"date": "2021-12-30", "close": 28.3, "volume": 12386300}, {"date": "2021-12-31", "close": 27.44, "volume": 14554500}, {"date": "2022-01-03", "close": 29.31, "volume": 19555600}, {"date": "2022-01-04", "close": 30.05, "volume": 20568400}, {"date": "2022-01-05", "close": 29.75, "volume": 18118900}, {"date": "2022-01-06", "close": 29.75, "volume": 11555100}, {"date": "2022-01-07", "close": 32.18, "volume": 27736100}, {"date": "2022-01-10", "close": 31.74, "volume": 21648300}, {"date": "2022-01-11", "close": 31.79, "volume": 9730600}, {"date": "2022-01-12", "close": 31.8, "volume": 8473900}, {"date": "2022-01-13", "close": 32.9, "volume": 15606600}, {"date": "2022-01-14", "close": 33.48, "volume": 10259000}, {"date": "2022-01-18", "close": 32.01, "volume": 20056700}, {"date": "2022-01-19", "close": 31.89, "volume": 18207400}, {"date": "2022-01-20", "close": 30.67, "volume": 15664500}, {"date": "2022-01-21", "close": 28.41, "volume": 21435800}, {"date": "2022-01-24", "close": 29.6, "volume": 18787300}, {"date": "2022-01-25", "close": 29.88, "volume": 11808800}, {"date": "2022-01-26", "close": 28.8, "volume": 15505200}, {"date": "2022-01-27", "close": 28.56, "volume": 14309800}, {"date": "2022-01-28", "close": 29.98, "volume": 14852900}, {"date": "2022-01-31", "close": 30.41, "volume": 10162300}, {"date": "2022-02-01", "close": 30.64, "volume": 8991500}, {"date": "2022-02-02", "close": 29.8, "volume": 10144600}, {"date": "2022-02-03", "close": 30.1, "volume": 9594900}, {"date": "2022-02-04", "close": 30.38, "volume": 8516300}, {"date": "2022-02-07", "close": 30.91, "volume": 8546300}, {"date": "2022-02-08", "close": 31.4, "volume": 9715300}, {"date": "2022-02-09", "close": 32.53, "volume": 10466300}, {"date": "2022-02-10", "close": 32.62, "volume": 11436200}, {"date": "2022-02-11", "close": 32.73, "volume": 10450100}, {"date": "2022-02-14", "close": 31.85, "volume": 10548200}, {"date": "2022-02-15", "close": 32.72, "volume": 13294700}, {"date": "2022-02-16", "close": 26.89, "volume": 87606200}, {"date": "2022-02-17", "close": 26.69, "volume": 12100500}, {"date": "2022-02-18", "close": 25.8, "volume": 17020000}, {"date": "2022-02-22", "close": 25.32, "volume": 13261100}, {"date": "2022-02-23", "close": 25.82, "volume": 14566900}, {"date": "2022-02-24", "close": 26.41, "volume": 13670600}, {"date": "2022-02-25", "close": 26.88, "volume": 9130000}, {"date": "2022-02-28", "close": 27.83, "volume": 23784100}, {"date": "2022-03-01", "close": 29.33, "volume": 21537700}, {"date": "2022-03-02", "close": 32.04, "volume": 30575500}, {"date": "2022-03-03", "close": 32.22, "volume": 15983400}, {"date": "2022-03-04", "close": 30.98, "volume": 17458900}, {"date": "2022-03-07", "close": 30.48, "volume": 14670000}, {"date": "2022-03-08", "close": 30.69, "volume": 12438500}, {"date": "2022-03-09", "close": 30.68, "volume": 8303800}, {"date": "2022-03-10", "close": 30.21, "volume": 10428900}, {"date": "2022-03-11", "close": 29.66, "volume": 6783900}, {"date": "2022-03-14", "close": 32.76, "volume": 25229200}, {"date": "2022-03-15", "close": 32.25, "volume": 13143100}, {"date": "2022-03-16", "close": 33.2, "volume": 10120500}, {"date": "2022-03-17", "close": 33.77, "volume": 9887800}, {"date": "2022-03-18", "close": 33.97, "volume": 26711400}, {"date": "2022-03-21", "close": 33.34, "volume": 9914000}, {"date": "2022-03-22", "close": 34.28, "volume": 15019400}, {"date": "2022-03-23", "close": 34.46, "volume": 8950100}, {"date": "2022-03-24", "close": 34.71, "volume": 5347500}, {"date": "2022-03-25", "close": 35.25, "volume": 7591800}, {"date": "2022-03-28", "close": 34.44, "volume": 9030100}, {"date": "2022-03-29", "close": 34.97, "volume": 6210200}, {"date": "2022-03-30", "close": 34.9, "volume": 4589500}, {"date": "2022-03-31", "close": 34.63, "volume": 7264200}, {"date": "2022-04-01", "close": 34.26, "volume": 7748400}, {"date": "2022-04-04", "close": 34.55, "volume": 8486100}, {"date": "2022-04-05", "close": 33.74, "volume": 6770000}, {"date": "2022-04-06", "close": 32.84, "volume": 10361600}, {"date": "2022-04-07", "close": 32.34, "volume": 10673500}, {"date": "2022-04-08", "close": 32.92, "volume": 8966300}, {"date": "2022-04-11", "close": 32.89, "volume": 5494300}, {"date": "2022-04-12", "close": 33.03, "volume": 5670600}, {"date": "2022-04-13", "close": 33.19, "volume": 4497900}, {"date": "2022-04-14", "close": 33.35, "volume": 3950800}, {"date": "2022-04-18", "close": 32.95, "volume": 4182200}, {"date": "2022-04-19", "close": 33.23, "volume": 5788100}, {"date": "2022-04-20", "close": 30.37, "volume": 20866000}, {"date": "2022-04-21", "close": 29.59, "volume": 8322900}, {"date": "2022-04-22", "close": 28.43, "volume": 9089800}, {"date": "2022-04-25", "close": 28.58, "volume": 7009500}, {"date": "2022-04-26", "close": 26.9, "volume": 8956400}, {"date": "2022-04-27", "close": 26.5, "volume": 7891100}, {"date": "2022-04-28", "close": 26.61, "volume": 6742100}, {"date": "2022-04-29", "close": 26.67, "volume": 7523000}, {"date": "2022-05-02", "close": 27.73, "volume": 12111200}, {"date": "2022-05-03", "close": 27.37, "volume": 18703000}, {"date": "2022-05-04", "close": 27.64, "volume": 13527200}, {"date": "2022-05-05", "close": 27.22, "volume": 10597700}, {"date": "2022-05-06", "close": 25.56, "volume": 11249300}, {"date": "2022-05-09", "close": 25.13, "volume": 9804200}, {"date": "2022-05-10", "close": 25.12, "volume": 8890300}, {"date": "2022-05-11", "close": 24.45, "volume": 7066800}, {"date": "2022-05-12", "close": 24.84, "volume": 11178700}, {"date": "2022-05-13", "close": 25.97, "volume": 7768500}, {"date": "2022-05-16", "close": 25.67, "volume": 7932500}, {"date": "2022-05-17", "close": 29.6, "volume": 27198900}, {"date": "2022-05-18", "close": 28.9, "volume": 13586400}, {"date": "2022-05-19", "close": 29.51, "volume": 10148600}, {"date": "2022-05-20", "close": 29.9, "volume": 9845700}, {"date": "2022-05-23", "close": 30.31, "volume": 8864300}, {"date": "2022-05-24", "close": 29.13, "volume": 7081200}, {"date": "2022-05-25", "close": 29.63, "volume": 10647900}, {"date": "2022-05-26", "close": 29.68, "volume": 6418200}, {"date": "2022-05-27", "close": 31.06, "volume": 9179100}, {"date": "2022-05-31", "close": 31.45, "volume": 13664700}, {"date": "2022-06-01", "close": 29.63, "volume": 12810000}, {"date": "2022-06-02", "close": 28.79, "volume": 19731900}, {"date": "2022-06-03", "close": 28.21, "volume": 8669800}, {"date": "2022-06-06", "close": 27.86, "volume": 6316500}, {"date": "2022-06-07", "close": 27.99, "volume": 5179000}, {"date": "2022-06-08", "close": 28.16, "volume": 4649600}, {"date": "2022-06-09", "close": 26.7, "volume": 6872100}, {"date": "2022-06-10", "close": 25.73, "volume": 10028800}, {"date": "2022-06-13", "close": 23.64, "volume": 19415400}, {"date": "2022-06-14", "close": 23.49, "volume": 13727100}, {"date": "2022-06-15", "close": 23.72, "volume": 9804300}, {"date": "2022-06-16", "close": 22.42, "volume": 14417200}, {"date": "2022-06-17", "close": 22.71, "volume": 14331300}, {"date": "2022-06-21", "close": 22.74, "volume": 10581800}, {"date": "2022-06-22", "close": 22.6, "volume": 6624400}, {"date": "2022-06-23", "close": 22.67, "volume": 5325000}, {"date": "2022-06-24", "close": 23.82, "volume": 7962300}, {"date": "2022-06-27", "close": 24.02, "volume": 5007100}, {"date": "2022-06-28", "close": 23.63, "volume": 4538200}, {"date": "2022-06-29", "close": 23.19, "volume": 5194600}, {"date": "2022-06-30", "close": 22.82, "volume": 6891400}, {"date": "2022-07-01", "close": 23.31, "volume": 6442000}, {"date": "2022-07-05", "close": 23.29, "volume": 7952600}, {"date": "2022-07-06", "close": 23.17, "volume": 5869700}, {"date": "2022-07-07", "close": 23.95, "volume": 5666700}, {"date": "2022-07-08", "close": 23.63, "volume": 10021500}, {"date": "2022-07-11", "close": 22.35, "volume": 10025000}, {"date": "2022-07-12", "close": 23.2, "volume": 7581900}, {"date": "2022-07-13", "close": 23.13, "volume": 4768700}, {"date": "2022-07-14", "close": 22.3, "volume": 6283700}, {"date": "2022-07-15", "close": 23.11, "volume": 6640700}, {"date": "2022-07-18", "close": 22.67, "volume": 11639300}, {"date": "2022-07-19", "close": 23.16, "volume": 9739400}, {"date": "2022-07-20", "close": 24.05, "volume": 10033600}, {"date": "2022-07-21", "close": 24.06, "volume": 6386200}, {"date": "2022-07-22", "close": 23.36, "volume": 7962500}, {"date": "2022-07-25", "close": 23.43, "volume": 6291800}, {"date": "2022-07-26", "close": 22.32, "volume": 9745800}, {"date": "2022-07-27", "close": 22.68, "volume": 6505000}, {"date": "2022-07-28", "close": 22.51, "volume": 9365100}, {"date": "2022-07-29", "close": 21.87, "volume": 15451700}, {"date": "2022-08-01", "close": 22.33, "volume": 6976600}, {"date": "2022-08-02", "close": 22.62, "volume": 6494400}, {"date": "2022-08-03", "close": 23.15, "volume": 10863100}, {"date": "2022-08-04", "close": 23.4, "volume": 14790000}, {"date": "2022-08-05", "close": 22.43, "volume": 14571200}, {"date": "2022-08-08", "close": 23.31, "volume": 11387500}, {"date": "2022-08-09", "close": 22.83, "volume": 11436500}, {"date": "2022-08-10", "close": 23.2, "volume": 6785100}, {"date": "2022-08-11", "close": 23.85, "volume": 9007100}, {"date": "2022-08-12", "close": 24.21, "volume": 5761400}, {"date": "2022-08-15", "close": 24.56, "volume": 12383700}, {"date": "2022-08-16", "close": 25.15, "volume": 11285700}, {"date": "2022-08-17", "close": 24.32, "volume": 7213200}, {"date": "2022-08-18", "close": 24.01, "volume": 7053100}, {"date": "2022-08-19", "close": 23.95, "volume": 8227400}, {"date": "2022-08-22", "close": 22.71, "volume": 13121400}, {"date": "2022-08-23", "close": 22.65, "volume": 8362700}, {"date": "2022-08-24", "close": 23.12, "volume": 6255900}, {"date": "2022-08-25", "close": 23.98, "volume": 5789400}, {"date": "2022-08-26", "close": 23.02, "volume": 12397100}, {"date": "2022-08-29", "close": 22.5, "volume": 6339300}, {"date": "2022-08-30", "close": 22.24, "volume": 12212100}, {"date": "2022-08-31", "close": 21.63, "volume": 9959800}, {"date": "2022-09-01", "close": 21.69, "volume": 9014800}, {"date": "2022-09-02", "close": 21.38, "volume": 10100400}, {"date": "2022-09-06", "close": 21.17, "volume": 16381600}, {"date": "2022-09-07", "close": 21.23, "volume": 9966400}, {"date": "2022-09-08", "close": 21.0, "volume": 10065200}, {"date": "2022-09-09", "close": 21.88, "volume": 9158000}, {"date": "2022-09-12", "close": 22.43, "volume": 7972300}, {"date": "2022-09-13", "close": 20.83, "volume": 13391200}, {"date": "2022-09-14", "close": 20.48, "volume": 14941100}, {"date": "2022-09-15", "close": 21.54, "volume": 14745200}, {"date": "2022-09-16", "close": 21.24, "volume": 31555800}, {"date": "2022-09-19", "close": 21.59, "volume": 6730000}, {"date": "2022-09-20", "close": 21.13, "volume": 7830800}, {"date": "2022-09-21", "close": 20.0, "volume": 8761200}, {"date": "2022-09-22", "close": 19.5, "volume": 9425900}, {"date": "2022-09-23", "close": 18.85, "volume": 14644900}, {"date": "2022-09-26", "close": 18.37, "volume": 12885000}, {"date": "2022-09-27", "close": 18.13, "volume": 9752500}, {"date": "2022-09-28", "close": 18.53, "volume": 7789800}, {"date": "2022-09-29", "close": 17.71, "volume": 12029000}, {"date": "2022-09-30", "close": 17.79, "volume": 9136300}, {"date": "2022-10-03", "close": 18.34, "volume": 8446900}, {"date": "2022-10-04", "close": 18.76, "volume": 10613700}, {"date": "2022-10-05", "close": 18.29, "volume": 11594800}, {"date": "2022-10-06", "close": 17.88, "volume": 10672300}, {"date": "2022-10-07", "close": 17.43, "volume": 9161200}, {"date": "2022-10-10", "close": 17.34, "volume": 6246900}, {"date": "2022-10-11", "close": 17.05, "volume": 8786400}, {"date": "2022-10-12", "close": 17.33, "volume": 6771200}, {"date": "2022-10-13", "close": 17.9, "volume": 9972800}, {"date": "2022-10-14", "close": 17.54, "volume": 5577000}, {"date": "2022-10-17", "close": 18.03, "volume": 9154000}, {"date": "2022-10-18", "close": 18.31, "volume": 7659400}, {"date": "2022-10-19", "close": 17.83, "volume": 7266600}, {"date": "2022-10-20", "close": 17.86, "volume": 5938700}, {"date": "2022-10-21", "close": 17.96, "volume": 9725000}, {"date": "2022-10-24", "close": 17.84, "volume": 6977900}, {"date": "2022-10-25", "close": 18.38, "volume": 6681400}, {"date": "2022-10-26", "close": 18.07, "volume": 8154700}, {"date": "2022-10-27", "close": 17.2, "volume": 12711200}, {"date": "2022-10-28", "close": 17.77, "volume": 8907300}, {"date": "2022-10-31", "close": 17.12, "volume": 16357100}, {"date": "2022-11-01", "close": 17.91, "volume": 14504100}, {"date": "2022-11-02", "close": 15.69, "volume": 34636100}, {"date": "2022-11-03", "close": 15.15, "volume": 20763900}, {"date": "2022-11-04", "close": 14.55, "volume": 16457700}, {"date": "2022-11-07", "close": 15.3, "volume": 14246800}, {"date": "2022-11-08", "close": 15.49, "volume": 14945000}, {"date": "2022-11-09", "close": 14.51, "volume": 14495900}, {"date": "2022-11-10", "close": 15.48, "volume": 18009100}, {"date": "2022-11-11", "close": 17.58, "volume": 29935200}, {"date": "2022-11-14", "close": 17.28, "volume": 14656800}, {"date": "2022-11-15", "close": 18.17, "volume": 30421400}, {"date": "2022-11-16", "close": 16.95, "volume": 19353300}, {"date": "2022-11-17", "close": 17.2, "volume": 12968200}, {"date": "2022-11-18", "close": 17.44, "volume": 10379800}, {"date": "2022-11-21", "close": 17.31, "volume": 8575300}, {"date": "2022-11-22", "close": 17.89, "volume": 11642100}, {"date": "2022-11-23", "close": 18.37, "volume": 8468600}, {"date": "2022-11-25", "close": 18.61, "volume": 4850300}, {"date": "2022-11-28", "close": 17.98, "volume": 7794400}, {"date": "2022-11-29", "close": 18.46, "volume": 8143900}, {"date": "2022-11-30", "close": 18.77, "volume": 11839600}, {"date": "2022-12-01", "close": 18.85, "volume": 10115200}, {"date": "2022-12-02", "close": 19.05, "volume": 7513400}, {"date": "2022-12-05", "close": 18.23, "volume": 11282500}, {"date": "2022-12-06", "close": 16.96, "volume": 21050800}, {"date": "2022-12-07", "close": 16.83, "volume": 10483800}, {"date": "2022-12-08", "close": 16.91, "volume": 11494600}, {"date": "2022-12-09", "close": 17.77, "volume": 13049400}, {"date": "2022-12-12", "close": 18.38, "volume": 14828800}, {"date": "2022-12-13", "close": 18.38, "volume": 16741500}, {"date": "2022-12-14", "close": 18.32, "volume": 8312800}, {"date": "2022-12-15", "close": 16.71, "volume": 17240400}, {"date": "2022-12-16", "close": 16.38, "volume": 23845900}, {"date": "2022-12-19", "close": 16.01, "volume": 11286600}, {"date": "2022-12-20", "close": 15.97, "volume": 15489700}, {"date": "2022-12-21", "close": 15.97, "volume": 9827000}, {"date": "2022-12-22", "close": 16.03, "volume": 8433800}, {"date": "2022-12-23", "close": 15.76, "volume": 9685800}, {"date": "2022-12-27", "close": 15.63, "volume": 8231100}, {"date": "2022-12-28", "close": 15.24, "volume": 8819200}, {"date": "2022-12-29", "close": 15.87, "volume": 10443200}, {"date": "2022-12-30", "close": 15.97, "volume": 9652200}, {"date": "2023-01-03", "close": 16.15, "volume": 12693300}, {"date": "2023-01-04", "close": 17.5, "volume": 13236100}, {"date": "2023-01-05", "close": 17.65, "volume": 8568600}, {"date": "2023-01-06", "close": 18.0, "volume": 8439300}, {"date": "2023-01-09", "close": 18.5, "volume": 10371600}, {"date": "2023-01-10", "close": 18.82, "volume": 9916200}, {"date": "2023-01-11", "close": 18.92, "volume": 11009200}, {"date": "2023-01-12", "close": 19.14, "volume": 8381300}, {"date": "2023-01-13", "close": 18.98, "volume": 7647300}, {"date": "2023-01-17", "close": 19.53, "volume": 10509800}, {"date": "2023-01-18", "close": 18.94, "volume": 9207700}, {"date": "2023-01-19", "close": 18.51, "volume": 9280000}, {"date": "2023-01-20", "close": 19.21, "volume": 8541200}, {"date": "2023-01-23", "close": 20.02, "volume": 9105200}, {"date": "2023-01-24", "close": 19.71, "volume": 5835200}, {"date": "2023-01-25", "close": 20.75, "volume": 12569900}, {"date": "2023-01-26", "close": 21.2, "volume": 17152600}, {"date": "2023-01-27", "close": 21.83, "volume": 12597300}, {"date": "2023-01-30", "close": 21.39, "volume": 9024100}, {"date": "2023-01-31", "close": 21.91, "volume": 27171400}, {"date": "2023-02-01", "close": 23.08, "volume": 16302100}, {"date": "2023-02-02", "close": 23.89, "volume": 20276500}, {"date": "2023-02-03", "close": 23.27, "volume": 7279400}, {"date": "2023-02-06", "close": 22.76, "volume": 8478100}, {"date": "2023-02-07", "close": 22.09, "volume": 9283200}, {"date": "2023-02-08", "close": 21.21, "volume": 9786300}, {"date": "2023-02-09", "close": 20.61, "volume": 10279700}, {"date": "2023-02-10", "close": 20.43, "volume": 7748100}, {"date": "2023-02-13", "close": 21.11, "volume": 8906700}, {"date": "2023-02-14", "close": 21.24, "volume": 7773500}, {"date": "2023-02-15", "close": 23.22, "volume": 23919000}, {"date": "2023-02-16", "close": 22.23, "volume": 26736800}, {"date": "2023-02-17", "close": 22.41, "volume": 18133900}, {"date": "2023-02-21", "close": 21.69, "volume": 12343200}, {"date": "2023-02-22", "close": 22.04, "volume": 8819900}, {"date": "2023-02-23", "close": 22.18, "volume": 10965500}, {"date": "2023-02-24", "close": 21.1, "volume": 13419000}, {"date": "2023-02-27", "close": 20.9, "volume": 11372000}, {"date": "2023-02-28", "close": 20.26, "volume": 13354200}, {"date": "2023-03-01", "close": 20.55, "volume": 9925000}, {"date": "2023-03-02", "close": 21.14, "volume": 8009100}, {"date": "2023-03-03", "close": 21.37, "volume": 7552400}, {"date": "2023-03-06", "close": 20.85, "volume": 9241900}, {"date": "2023-03-07", "close": 20.32, "volume": 7756800}, {"date": "2023-03-08", "close": 20.69, "volume": 7210700}, {"date": "2023-03-09", "close": 19.73, "volume": 9073800}, {"date": "2023-03-10", "close": 18.82, "volume": 11895200}, {"date": "2023-03-13", "close": 18.35, "volume": 15789700}, {"date": "2023-03-14", "close": 18.59, "volume": 10390100}, {"date": "2023-03-15", "close": 18.73, "volume": 11795700}, {"date": "2023-03-16", "close": 18.89, "volume": 10474100}, {"date": "2023-03-17", "close": 18.86, "volume": 28213400}, {"date": "2023-03-20", "close": 19.15, "volume": 7202400}, {"date": "2023-03-21", "close": 20.35, "volume": 11417300}, {"date": "2023-03-22", "close": 19.81, "volume": 8618700}, {"date": "2023-03-23", "close": 19.86, "volume": 7610500}, {"date": "2023-03-24", "close": 19.37, "volume": 10231600}, {"date": "2023-03-27", "close": 19.88, "volume": 5256700}, {"date": "2023-03-28", "close": 20.5, "volume": 16222600}, {"date": "2023-03-29", "close": 20.6, "volume": 8438700}, {"date": "2023-03-30", "close": 20.79, "volume": 5987300}, {"date": "2023-03-31", "close": 21.36, "volume": 9649700}, {"date": "2023-04-03", "close": 20.87, "volume": 11501100}, {"date": "2023-04-04", "close": 20.69, "volume": 9940300}, {"date": "2023-04-05", "close": 20.11, "volume": 10836400}, {"date": "2023-04-06", "close": 20.74, "volume": 8478000}, {"date": "2023-04-10", "close": 21.35, "volume": 7208000}, {"date": "2023-04-11", "close": 21.91, "volume": 13385900}, {"date": "2023-04-12", "close": 21.19, "volume": 10768900}, {"date": "2023-04-13", "close": 21.2, "volume": 9708500}, {"date": "2023-04-14", "close": 20.66, "volume": 8089200}, {"date": "2023-04-17", "close": 21.14, "volume": 6431900}, {"date": "2023-04-18", "close": 20.89, "volume": 5583100}, {"date": "2023-04-19", "close": 21.6, "volume": 10613400}, {"date": "2023-04-20", "close": 21.21, "volume": 8104200}, {"date": "2023-04-21", "close": 21.57, "volume": 7918700}, {"date": "2023-04-24", "close": 21.62, "volume": 8892800}, {"date": "2023-04-25", "close": 21.04, "volume": 9405900}, {"date": "2023-04-26", "close": 20.73, "volume": 5664000}, {"date": "2023-04-27", "close": 22.1, "volume": 11427300}, {"date": "2023-04-28", "close": 22.34, "volume": 9519100}, {"date": "2023-05-01", "close": 22.45, "volume": 9924400}, {"date": "2023-05-02", "close": 22.01, "volume": 11174600}, {"date": "2023-05-03", "close": 21.92, "volume": 11986000}, {"date": "2023-05-04", "close": 15.7, "volume": 72171000}, {"date": "2023-05-05", "close": 16.14, "volume": 52342100}, {"date": "2023-05-08", "close": 16.27, "volume": 18853400}, {"date": "2023-05-09", "close": 15.83, "volume": 14977700}, {"date": "2023-05-10", "close": 15.18, "volume": 18320700}, {"date": "2023-05-11", "close": 14.72, "volume": 19051700}, {"date": "2023-05-12", "close": 14.38, "volume": 14403600}, {"date": "2023-05-15", "close": 15.14, "volume": 14599700}, {"date": "2023-05-16", "close": 14.32, "volume": 16927600}, {"date": "2023-05-17", "close": 14.91, "volume": 15776200}, {"date": "2023-05-18", "close": 15.04, "volume": 17445700}, {"date": "2023-05-19", "close": 14.53, "volume": 11065700}, {"date": "2023-05-22", "close": 14.35, "volume": 18178400}, {"date": "2023-05-23", "close": 14.29, "volume": 19687400}, {"date": "2023-05-24", "close": 14.02, "volume": 24032100}, {"date": "2023-05-25", "close": 13.48, "volume": 28822700}, {"date": "2023-05-26", "close": 14.28, "volume": 26299800}, {"date": "2023-05-30", "close": 15.19, "volume": 26061500}, {"date": "2023-05-31", "close": 14.56, "volume": 46194200}, {"date": "2023-06-01", "close": 14.74, "volume": 11966100}, {"date": "2023-06-02", "close": 14.75, "volume": 12417900}, {"date": "2023-06-05", "close": 14.49, "volume": 12354500}, {"date": "2023-06-06", "close": 15.12, "volume": 12253400}, {"date": "2023-06-07", "close": 15.7, "volume": 28373600}, {"date": "2023-06-08", "close": 15.88, "volume": 14195600}, {"date": "2023-06-09", "close": 15.42, "volume": 13686200}, {"date": "2023-06-12", "close": 15.81, "volume": 11436300}, {"date": "2023-06-13", "close": 15.91, "volume": 9224900}, {"date": "2023-06-14", "close": 15.94, "volume": 10376300}, {"date": "2023-06-15", "close": 15.88, "volume": 10109400}, {"date": "2023-06-16", "close": 15.64, "volume": 13016000}, {"date": "2023-06-20", "close": 15.05, "volume": 11601200}, {"date": "2023-06-21", "close": 15.12, "volume": 20746300}, {"date": "2023-06-22", "close": 14.94, "volume": 10108700}, {"date": "2023-06-23", "close": 14.75, "volume": 8522300}, {"date": "2023-06-26", "close": 14.95, "volume": 9242600}, {"date": "2023-06-27", "close": 15.25, "volume": 11224900}, {"date": "2023-06-28", "close": 15.12, "volume": 7278900}, {"date": "2023-06-29", "close": 15.36, "volume": 9163000}, {"date": "2023-06-30", "close": 15.28, "volume": 8376700}, {"date": "2023-07-03", "close": 15.67, "volume": 5382900}, {"date": "2023-07-05", "close": 15.51, "volume": 9928100}, {"date": "2023-07-06", "close": 15.82, "volume": 9911500}, {"date": "2023-07-07", "close": 15.65, "volume": 12992100}, {"date": "2023-07-10", "close": 15.6, "volume": 11417800}, {"date": "2023-07-11", "close": 16.16, "volume": 9404800}, {"date": "2023-07-12", "close": 15.89, "volume": 13612500}, {"date": "2023-07-13", "close": 16.15, "volume": 11985900}, {"date": "2023-07-14", "close": 15.33, "volume": 16266200}, {"date": "2023-07-17", "close": 14.75, "volume": 18671400}, {"date": "2023-07-18", "close": 14.91, "volume": 12672900}, {"date": "2023-07-19", "close": 15.41, "volume": 12852000}, {"date": "2023-07-20", "close": 15.27, "volume": 7502300}, {"date": "2023-07-21", "close": 14.91, "volume": 12118100}, {"date": "2023-07-24", "close": 14.87, "volume": 8893300}, {"date": "2023-07-25", "close": 14.5, "volume": 9463900}, {"date": "2023-07-26", "close": 14.88, "volume": 7211300}, {"date": "2023-07-27", "close": 14.45, "volume": 10479500}, {"date": "2023-07-28", "close": 14.72, "volume": 7631700}, {"date": "2023-07-31", "close": 15.4, "volume": 12208100}, {"date": "2023-08-01", "close": 15.42, "volume": 8947300}, {"date": "2023-08-02", "close": 14.94, "volume": 9222900}, {"date": "2023-08-03", "close": 14.49, "volume": 12955400}, {"date": "2023-08-04", "close": 15.01, "volume": 11777400}, {"date": "2023-08-07", "close": 15.45, "volume": 20930100}, {"date": "2023-08-08", "close": 15.7, "volume": 22037000}, {"date": "2023-08-09", "close": 15.0, "volume": 10864200}, {"date": "2023-08-10", "close": 14.86, "volume": 10570500}, {"date": "2023-08-11", "close": 14.67, "volume": 9845400}, {"date": "2023-08-14", "close": 14.34, "volume": 14998800}, {"date": "2023-08-15", "close": 14.76, "volume": 10156700}, {"date": "2023-08-16", "close": 14.4, "volume": 7086300}, {"date": "2023-08-17", "close": 13.97, "volume": 13194400}, {"date": "2023-08-18", "close": 14.22, "volume": 8817700}, {"date": "2023-08-21", "close": 14.06, "volume": 7215600}, {"date": "2023-08-22", "close": 13.97, "volume": 6447100}, {"date": "2023-08-23", "close": 14.41, "volume": 7547600}, {"date": "2023-08-24", "close": 14.15, "volume": 5919700}, {"date": "2023-08-25", "close": 13.87, "volume": 7713500}, {"date": "2023-08-28", "close": 14.16, "volume": 7048800}, {"date": "2023-08-29", "close": 14.37, "volume": 6560900}, {"date": "2023-08-30", "close": 14.5, "volume": 6440300}, {"date": "2023-08-31", "close": 14.49, "volume": 6727400}, {"date": "2023-09-01", "close": 13.11, "volume": 32745300}, {"date": "2023-09-05", "close": 13.11, "volume": 12582600}, {"date": "2023-09-06", "close": 12.87, "volume": 15497300}, {"date": "2023-09-07", "close": 12.51, "volume": 20686600}, {"date": "2023-09-08", "close": 13.12, "volume": 13775600}, {"date": "2023-09-11", "close": 13.01, "volume": 19227900}, {"date": "2023-09-12", "close": 12.98, "volume": 10494400}, {"date": "2023-09-13", "close": 12.84, "volume": 10485800}, {"date": "2023-09-14", "close": 13.29, "volume": 9988800}, {"date": "2023-09-15", "close": 13.55, "volume": 18420100}, {"date": "2023-09-18", "close": 13.11, "volume": 9015800}, {"date": "2023-09-19", "close": 13.11, "volume": 6225600}, {"date": "2023-09-20", "close": 12.76, "volume": 7217200}, {"date": "2023-09-21", "close": 12.82, "volume": 9280500}, {"date": "2023-09-22", "close": 12.19, "volume": 20955900}, {"date": "2023-09-25", "close": 12.21, "volume": 16022300}, {"date": "2023-09-26", "close": 12.01, "volume": 9873900}, {"date": "2023-09-27", "close": 12.32, "volume": 9315700}, {"date": "2023-09-28", "close": 12.36, "volume": 6734000}, {"date": "2023-09-29", "close": 12.44, "volume": 8590300}, {"date": "2023-10-02", "close": 12.14, "volume": 7348000}, {"date": "2023-10-03", "close": 11.56, "volume": 17170700}, {"date": "2023-10-04", "close": 11.4, "volume": 12779100}, {"date": "2023-10-05", "close": 11.25, "volume": 12905300}, {"date": "2023-10-06", "close": 11.4, "volume": 11786000}, {"date": "2023-10-09", "close": 11.53, "volume": 9989000}, {"date": "2023-10-10", "close": 11.98, "volume": 8911300}, {"date": "2023-10-11", "close": 11.7, "volume": 7185300}, {"date": "2023-10-12", "close": 11.31, "volume": 8953900}, {"date": "2023-10-13", "close": 11.47, "volume": 8957500}, {"date": "2023-10-16", "close": 11.82, "volume": 9516500}, {"date": "2023-10-17", "close": 12.01, "volume": 7986600}, {"date": "2023-10-18", "close": 11.75, "volume": 6197000}, {"date": "2023-10-19", "close": 11.36, "volume": 11896000}, {"date": "2023-10-20", "close": 11.09, "volume": 9714800}, {"date": "2023-10-23", "close": 10.79, "volume": 13490700}, {"date": "2023-10-24", "close": 10.75, "volume": 13659000}, {"date": "2023-10-25", "close": 10.55, "volume": 12903900}, {"date": "2023-10-26", "close": 10.51, "volume": 12000800}, {"date": "2023-10-27", "close": 10.32, "volume": 11126900}, {"date": "2023-10-30", "close": 10.6, "volume": 13337400}, {"date": "2023-10-31", "close": 10.49, "volume": 15194100}, {"date": "2023-11-01", "close": 10.41, "volume": 16678200}, {"date": "2023-11-02", "close": 11.49, "volume": 23944800}, {"date": "2023-11-03", "close": 13.27, "volume": 31936400}, {"date": "2023-11-06", "close": 12.23, "volume": 22297000}, {"date": "2023-11-07", "close": 12.38, "volume": 12593400}, {"date": "2023-11-08", "close": 11.4, "volume": 24142800}, {"date": "2023-11-09", "close": 11.69, "volume": 18170000}, {"date": "2023-11-10", "close": 11.67, "volume": 9588600}, {"date": "2023-11-13", "close": 11.57, "volume": 8205800}, {"date": "2023-11-14", "close": 12.07, "volume": 16142300}, {"date": "2023-11-15", "close": 12.7, "volume": 11573500}, {"date": "2023-11-16", "close": 12.3, "volume": 12066000}, {"date": "2023-11-17", "close": 12.72, "volume": 9407700}, {"date": "2023-11-20", "close": 13.43, "volume": 21637600}, {"date": "2023-11-21", "close": 13.55, "volume": 16462800}, {"date": "2023-11-22", "close": 13.65, "volume": 15799100}, {"date": "2023-11-24", "close": 13.7, "volume": 3299700}, {"date": "2023-11-27", "close": 13.64, "volume": 7085400}, {"date": "2023-11-28", "close": 13.41, "volume": 11999500}, {"date": "2023-11-29", "close": 13.89, "volume": 10677500}, {"date": "2023-11-30", "close": 13.85, "volume": 13241500}, {"date": "2023-12-01", "close": 15.21, "volume": 30992200}, {"date": "2023-12-04", "close": 15.38, "volume": 13153200}, {"date": "2023-12-05", "close": 14.95, "volume": 12367500}, {"date": "2023-12-06", "close": 14.67, "volume": 9695600}, {"date": "2023-12-07", "close": 14.49, "volume": 9889100}, {"date": "2023-12-08", "close": 16.24, "volume": 49773400}, {"date": "2023-12-11", "close": 15.66, "volume": 26904100}, {"date": "2023-12-12", "close": 14.72, "volume": 19420900}, {"date": "2023-12-13", "close": 15.16, "volume": 26230000}, {"date": "2023-12-14", "close": 16.16, "volume": 20096000}, {"date": "2023-12-15", "close": 15.74, "volume": 24281300}, {"date": "2023-12-18", "close": 15.0, "volume": 14119800}, {"date": "2023-12-19", "close": 15.3, "volume": 14748900}, {"date": "2023-12-20", "close": 14.99, "volume": 36752800}, {"date": "2023-12-21", "close": 14.57, "volume": 30003100}, {"date": "2023-12-22", "close": 14.51, "volume": 17819000}, {"date": "2023-12-26", "close": 14.53, "volume": 12556500}, {"date": "2023-12-27", "close": 14.5, "volume": 9116200}, {"date": "2023-12-28", "close": 14.65, "volume": 21671700}, {"date": "2023-12-29", "close": 14.3, "volume": 12177900}, {"date": "2024-01-02", "close": 13.93, "volume": 14285900}, {"date": "2024-01-03", "close": 13.72, "volume": 14447400}, {"date": "2024-01-04", "close": 14.01, "volume": 10727600}, {"date": "2024-01-05", "close": 14.17, "volume": 12739800}, {"date": "2024-01-08", "close": 14.21, "volume": 12360800}, {"date": "2024-01-09", "close": 13.76, "volume": 10562000}, {"date": "2024-01-10", "close": 13.66, "volume": 21357300}, {"date": "2024-01-11", "close": 12.91, "volume": 19492100}, {"date": "2024-01-12", "close": 12.89, "volume": 12371300}, {"date": "2024-01-16", "close": 12.8, "volume": 11028800}, {"date": "2024-01-17", "close": 12.57, "volume": 10282900}, {"date": "2024-01-18", "close": 12.68, "volume": 7927900}, {"date": "2024-01-19", "close": 12.96, "volume": 13799700}, {"date": "2024-01-22", "close": 13.3, "volume": 11615900}, {"date": "2024-01-23", "close": 13.23, "volume": 9361500}, {"date": "2024-01-24", "close": 12.92, "volume": 17391900}, {"date": "2024-01-25", "close": 13.5, "volume": 30678900}, {"date": "2024-01-26", "close": 13.35, "volume": 8992600}, {"date": "2024-01-29", "close": 13.3, "volume": 8470100}, {"date": "2024-01-30", "close": 13.23, "volume": 8704100}, {"date": "2024-01-31", "close": 14.11, "volume": 71655800}, {"date": "2024-02-01", "close": 14.2, "volume": 16944300}, {"date": "2024-02-02", "close": 13.96, "volume": 14524400}, {"date": "2024-02-05", "close": 13.56, "volume": 13217600}, {"date": "2024-02-06", "close": 13.53, "volume": 11769800}, {"date": "2024-02-07", "close": 12.43, "volume": 27707100}, {"date": "2024-02-08", "close": 12.58, "volume": 12737800}, {"date": "2024-02-09", "close": 12.48, "volume": 9780300}, {"date": "2024-02-12", "close": 12.97, "volume": 18549900}, {"date": "2024-02-13", "close": 12.57, "volume": 15176500}, {"date": "2024-02-14", "close": 12.76, "volume": 12184200}, {"date": "2024-02-15", "close": 12.18, "volume": 20832800}, {"date": "2024-02-16", "close": 11.61, "volume": 21617200}, {"date": "2024-02-20", "close": 11.56, "volume": 13027000}, {"date": "2024-02-21", "close": 11.41, "volume": 10259800}, {"date": "2024-02-22", "close": 11.33, "volume": 11178600}, {"date": "2024-02-23", "close": 10.84, "volume": 23106600}, {"date": "2024-02-26", "close": 10.73, "volume": 19461400}, {"date": "2024-02-27", "close": 10.88, "volume": 25111200}, {"date": "2024-02-28", "close": 10.7, "volume": 28898500}, {"date": "2024-02-29", "close": 10.68, "volume": 38591000}, {"date": "2024-03-01", "close": 10.59, "volume": 15587000}, {"date": "2024-03-04", "close": 9.96, "volume": 25771200}, {"date": "2024-03-05", "close": 9.87, "volume": 11957200}, {"date": "2024-03-06", "close": 10.15, "volume": 14075000}, {"date": "2024-03-07", "close": 10.45, "volume": 15283600}, {"date": "2024-03-08", "close": 10.57, "volume": 12173600}, {"date": "2024-03-11", "close": 11.24, "volume": 18432600}, {"date": "2024-03-12", "close": 11.21, "volume": 19020600}, {"date": "2024-03-13", "close": 11.3, "volume": 9810100}, {"date": "2024-03-14", "close": 10.94, "volume": 16119900}, {"date": "2024-03-15", "close": 10.89, "volume": 35215200}, {"date": "2024-03-18", "close": 10.88, "volume": 9527200}, {"date": "2024-03-19", "close": 10.87, "volume": 10960200}, {"date": "2024-03-20", "close": 12.15, "volume": 40555900}, {"date": "2024-03-21", "close": 11.48, "volume": 25037500}, {"date": "2024-03-22", "close": 10.93, "volume": 16685700}, {"date": "2024-03-25", "close": 11.12, "volume": 9294800}, {"date": "2024-03-26", "close": 11.04, "volume": 8956500}, {"date": "2024-03-27", "close": 11.36, "volume": 17754500}, {"date": "2024-03-28", "close": 11.43, "volume": 9850400}, {"date": "2024-04-01", "close": 11.41, "volume": 9544600}, {"date": "2024-04-02", "close": 11.42, "volume": 10179800}, {"date": "2024-04-03", "close": 13.13, "volume": 63228800}, {"date": "2024-04-04", "close": 12.01, "volume": 51854600}, {"date": "2024-04-05", "close": 11.63, "volume": 51436900}, {"date": "2024-04-08", "close": 10.74, "volume": 36881000}, {"date": "2024-04-09", "close": 10.66, "volume": 17748200}, {"date": "2024-04-10", "close": 10.2, "volume": 35124900}, {"date": "2024-04-11", "close": 10.95, "volume": 27581200}, {"date": "2024-04-12", "close": 10.65, "volume": 14768800}, {"date": "2024-04-15", "close": 10.59, "volume": 18417000}, {"date": "2024-04-16", "close": 10.13, "volume": 14883100}, {"date": "2024-04-17", "close": 10.5, "volume": 11543100}, {"date": "2024-04-18", "close": 10.66, "volume": 11669400}, {"date": "2024-04-19", "close": 12.08, "volume": 45625400}, {"date": "2024-04-22", "close": 12.02, "volume": 19616800}, {"date": "2024-04-23", "close": 12.37, "volume": 15385700}, {"date": "2024-04-24", "close": 12.32, "volume": 9629300}, {"date": "2024-04-25", "close": 11.83, "volume": 18338200}, {"date": "2024-04-26", "close": 11.57, "volume": 15347000}, {"date": "2024-04-29", "close": 11.9, "volume": 26501600}, {"date": "2024-04-30", "close": 11.06, "volume": 23834600}, {"date": "2024-05-01", "close": 11.91, "volume": 18519500}, {"date": "2024-05-02", "close": 13.46, "volume": 64803800}, {"date": "2024-05-03", "close": 12.52, "volume": 67049300}, {"date": "2024-05-06", "close": 12.91, "volume": 23587300}, {"date": "2024-05-07", "close": 12.52, "volume": 15564800}, {"date": "2024-05-08", "close": 12.45, "volume": 12066800}, {"date": "2024-05-09", "close": 12.7, "volume": 10530600}, {"date": "2024-05-10", "close": 12.68, "volume": 9494500}, {"date": "2024-05-13", "close": 12.64, "volume": 8930600}, {"date": "2024-05-14", "close": 11.98, "volume": 29621000}, {"date": "2024-05-15", "close": 12.2, "volume": 12064600}, {"date": "2024-05-16", "close": 12.28, "volume": 8150100}, {"date": "2024-05-17", "close": 11.67, "volume": 17127600}, {"date": "2024-05-20", "close": 11.67, "volume": 10345300}, {"date": "2024-05-21", "close": 11.75, "volume": 11484900}, {"date": "2024-05-22", "close": 11.85, "volume": 6800600}, {"date": "2024-05-23", "close": 11.45, "volume": 12475700}, {"date": "2024-05-24", "close": 11.62, "volume": 6795900}, {"date": "2024-05-28", "close": 11.67, "volume": 8082900}, {"date": "2024-05-29", "close": 11.36, "volume": 7820000}, {"date": "2024-05-30", "close": 11.48, "volume": 25535200}, {"date": "2024-05-31", "close": 11.57, "volume": 19774900}, {"date": "2024-06-03", "close": 12.43, "volume": 34518500}, {"date": "2024-06-04", "close": 11.89, "volume": 18380100}, {"date": "2024-06-05", "close": 11.73, "volume": 10877700}, {"date": "2024-06-06", "close": 11.63, "volume": 9480400}, {"date": "2024-06-07", "close": 11.67, "volume": 10860800}, {"date": "2024-06-10", "close": 11.64, "volume": 8942600}, {"date": "2024-06-11", "close": 10.72, "volume": 36348700}, {"date": "2024-06-12", "close": 10.8, "volume": 31180700}, {"date": "2024-06-13", "close": 10.05, "volume": 30459800}, {"date": "2024-06-14", "close": 9.88, "volume": 15167100}, {"date": "2024-06-17", "close": 9.59, "volume": 15370600}, {"date": "2024-06-18", "close": 9.38, "volume": 14859900}, {"date": "2024-06-20", "close": 9.82, "volume": 22311000}, {"date": "2024-06-21", "close": 9.91, "volume": 20933000}, {"date": "2024-06-24", "close": 10.04, "volume": 9452400}, {"date": "2024-06-25", "close": 9.87, "volume": 12852200}, {"date": "2024-06-26", "close": 9.73, "volume": 9644000}, {"date": "2024-06-27", "close": 10.01, "volume": 12023600}, {"date": "2024-06-28", "close": 10.14, "volume": 14708800}, {"date": "2024-07-01", "close": 9.9, "volume": 11285400}, {"date": "2024-07-02", "close": 10.46, "volume": 20170500}, {"date": "2024-07-03", "close": 11.19, "volume": 35905200}, {"date": "2024-07-05", "close": 11.53, "volume": 20846500}, {"date": "2024-07-08", "close": 10.91, "volume": 42675400}, {"date": "2024-07-09", "close": 11.25, "volume": 22295800}, {"date": "2024-07-10", "close": 11.42, "volume": 16335400}, {"date": "2024-07-11", "close": 11.45, "volume": 9200700}, {"date": "2024-07-12", "close": 11.28, "volume": 9730400}, {"date": "2024-07-15", "close": 11.3, "volume": 6543700}, {"date": "2024-07-16", "close": 11.66, "volume": 9595700}, {"date": "2024-07-17", "close": 11.59, "volume": 7943300}, {"date": "2024-07-18", "close": 11.35, "volume": 10673900}, {"date": "2024-07-19", "close": 11.24, "volume": 6278100}, {"date": "2024-07-22", "close": 11.26, "volume": 7978000}, {"date": "2024-07-23", "close": 11.46, "volume": 6932100}, {"date": "2024-07-24", "close": 11.37, "volume": 6750600}, {"date": "2024-07-25", "close": 11.19, "volume": 9255800}, {"date": "2024-07-26", "close": 10.92, "volume": 9816100}, {"date": "2024-07-29", "close": 10.8, "volume": 8021000}, {"date": "2024-07-30", "close": 10.97, "volume": 9522500}, {"date": "2024-07-31", "close": 11.15, "volume": 15478600}, {"date": "2024-08-01", "close": 10.84, "volume": 7553400}, {"date": "2024-08-02", "close": 10.74, "volume": 8915000}, {"date": "2024-08-05", "close": 10.28, "volume": 10478600}, {"date": "2024-08-06", "close": 10.2, "volume": 10465900}, {"date": "2024-08-07", "close": 10.21, "volume": 7896200}, {"date": "2024-08-08", "close": 9.97, "volume": 14892300}, {"date": "2024-08-09", "close": 10.05, "volume": 14193200}, {"date": "2024-08-12", "close": 10.07, "volume": 6385100}, {"date": "2024-08-13", "close": 10.04, "volume": 10119300}, {"date": "2024-08-14", "close": 9.99, "volume": 7187100}, {"date": "2024-08-15", "close": 10.7, "volume": 22511200}, {"date": "2024-08-16", "close": 10.74, "volume": 9840300}, {"date": "2024-08-19", "close": 10.81, "volume": 11324000}, {"date": "2024-08-20", "close": 10.68, "volume": 12681800}, {"date": "2024-08-21", "close": 10.82, "volume": 7176000}, {"date": "2024-08-22", "close": 10.91, "volume": 7863300}, {"date": "2024-08-23", "close": 11.09, "volume": 7642300}, {"date": "2024-08-26", "close": 11.06, "volume": 9390300}, {"date": "2024-08-27", "close": 10.27, "volume": 17312700}, {"date": "2024-08-28", "close": 10.44, "volume": 9517700}, {"date": "2024-08-29", "close": 10.21, "volume": 11261800}, {"date": "2024-08-30", "close": 10.22, "volume": 18652600}, {"date": "2024-09-03", "close": 10.17, "volume": 7184300}, {"date": "2024-09-04", "close": 10.21, "volume": 7891100}, {"date": "2024-09-05", "close": 10.13, "volume": 10023300}, {"date": "2024-09-06", "close": 9.85, "volume": 8040200}, {"date": "2024-09-09", "close": 10.06, "volume": 9985400}, {"date": "2024-09-10", "close": 9.85, "volume": 8484900}, {"date": "2024-09-11", "close": 9.74, "volume": 7634600}, {"date": "2024-09-12", "close": 10.01, "volume": 7202800}, {"date": "2024-09-13", "close": 10.32, "volume": 8732500}, {"date": "2024-09-16", "close": 10.22, "volume": 6489100}, {"date": "2024-09-17", "close": 10.24, "volume": 5793000}, {"date": "2024-09-18", "close": 10.36, "volume": 7193200}, {"date": "2024-09-19", "close": 10.26, "volume": 6670400}, {"date": "2024-09-20", "close": 10.17, "volume": 33505500}, {"date": "2024-09-23", "close": 10.18, "volume": 5902300}, {"date": "2024-09-24", "close": 10.35, "volume": 4747500}, {"date": "2024-09-25", "close": 10.35, "volume": 4942500}, {"date": "2024-09-26", "close": 10.45, "volume": 4399000}, {"date": "2024-09-27", "close": 10.58, "volume": 5269800}, {"date": "2024-09-30", "close": 10.42, "volume": 7416200}, {"date": "2024-10-01", "close": 10.4, "volume": 5953800}, {"date": "2024-10-02", "close": 10.23, "volume": 5171000}, {"date": "2024-10-03", "close": 10.25, "volume": 6605000}, {"date": "2024-10-04", "close": 10.32, "volume": 5152100}, {"date": "2024-10-07", "close": 10.32, "volume": 4937800}, {"date": "2024-10-08", "close": 10.3, "volume": 4109100}, {"date": "2024-10-09", "close": 10.35, "volume": 6750700}, {"date": "2024-10-10", "close": 10.14, "volume": 4974400}, {"date": "2024-10-11", "close": 10.15, "volume": 4382500}, {"date": "2024-10-14", "close": 10.17, "volume": 3350500}, {"date": "2024-10-15", "close": 10.3, "volume": 6693000}, {"date": "2024-10-16", "close": 10.32, "volume": 4658600}, {"date": "2024-10-17", "close": 10.13, "volume": 9025300}, {"date": "2024-10-18", "close": 10.25, "volume": 4590700}, {"date": "2024-10-21", "close": 10.11, "volume": 5225400}, {"date": "2024-10-22", "close": 10.07, "volume": 5931500}, {"date": "2024-10-23", "close": 10.11, "volume": 4890600}, {"date": "2024-10-24", "close": 10.1, "volume": 3633000}, {"date": "2024-10-25", "close": 10.07, "volume": 5719700}, {"date": "2024-10-28", "close": 10.23, "volume": 5253800}, {"date": "2024-10-29", "close": 10.27, "volume": 3973100}, {"date": "2024-10-30", "close": 10.45, "volume": 5231700}, {"date": "2024-10-31", "close": 10.73, "volume": 8559600}, {"date": "2024-11-01", "close": 10.77, "volume": 6577400}, {"date": "2024-11-04", "close": 10.66, "volume": 4809700}, {"date": "2024-11-05", "close": 10.88, "volume": 6898200}, {"date": "2024-11-06", "close": 11.16, "volume": 12576200}, {"date": "2024-11-07", "close": 11.31, "volume": 10617900}, {"date": "2024-11-08", "close": 10.86, "volume": 15682600}, {"date": "2024-11-11", "close": 11.33, "volume": 14093800}, {"date": "2024-11-12", "close": 11.23, "volume": 10026800}, {"date": "2024-11-13", "close": 10.94, "volume": 12007300}, {"date": "2024-11-14", "close": 11.13, "volume": 9294800}, {"date": "2024-11-15", "close": 10.63, "volume": 14795800}, {"date": "2024-11-18", "close": 10.41, "volume": 12238900}, {"date": "2024-11-19", "close": 10.13, "volume": 16248600}, {"date": "2024-11-20", "close": 10.38, "volume": 8702400}, {"date": "2024-11-21", "close": 10.88, "volume": 11221100}, {"date": "2024-11-22", "close": 10.67, "volume": 11242700}, {"date": "2024-11-25", "close": 10.91, "volume": 55191500}, {"date": "2024-11-26", "close": 10.43, "volume": 13048300}, {"date": "2024-11-27", "close": 10.56, "volume": 11266300}, {"date": "2024-11-29", "close": 10.64, "volume": 3651800}, {"date": "2024-12-02", "close": 10.77, "volume": 6265800}, {"date": "2024-12-03", "close": 10.71, "volume": 5923400}, {"date": "2024-12-04", "close": 10.81, "volume": 8061700}, {"date": "2024-12-05", "close": 10.6, "volume": 7051400}, {"date": "2024-12-06", "close": 10.78, "volume": 7609400}, {"date": "2024-12-09", "close": 10.95, "volume": 11064900}, {"date": "2024-12-10", "close": 10.98, "volume": 8990300}, {"date": "2024-12-11", "close": 10.97, "volume": 9915500}, {"date": "2024-12-12", "close": 11.41, "volume": 11272600}, {"date": "2024-12-13", "close": 11.0, "volume": 5618800}, {"date": "2024-12-16", "close": 10.82, "volume": 8274700}, {"date": "2024-12-17", "close": 10.65, "volume": 7242400}, {"date": "2024-12-18", "close": 10.52, "volume": 12328500}, {"date": "2024-12-19", "close": 10.42, "volume": 9067300}, {"date": "2024-12-20", "close": 10.5, "volume": 18990900}, {"date": "2024-12-23", "close": 10.2, "volume": 9671800}, {"date": "2024-12-24", "close": 10.26, "volume": 4116200}, {"date": "2024-12-26", "close": 10.28, "volume": 6849800}, {"date": "2024-12-27", "close": 10.25, "volume": 5766200}, {"date": "2024-12-30", "close": 10.19, "volume": 8242100}, {"date": "2024-12-31", "close": 10.3, "volume": 9559000}, {"date": "2025-01-02", "close": 10.42, "volume": 9216900}, {"date": "2025-01-03", "close": 10.51, "volume": 5765700}, {"date": "2025-01-06", "close": 10.77, "volume": 7853300}, {"date": "2025-01-07", "close": 10.73, "volume": 6841200}, {"date": "2025-01-08", "close": 10.48, "volume": 8025400}, {"date": "2025-01-10", "close": 10.32, "volume": 10085800}, {"date": "2025-01-13", "close": 10.56, "volume": 8253900}, {"date": "2025-01-14", "close": 10.51, "volume": 6133200}, {"date": "2025-01-15", "close": 10.28, "volume": 9453600}, {"date": "2025-01-16", "close": 10.01, "volume": 14965800}, {"date": "2025-01-17", "close": 10.12, "volume": 9459900}, {"date": "2025-01-21", "close": 10.32, "volume": 7972400}, {"date": "2025-01-22", "close": 10.35, "volume": 10114900}, {"date": "2025-01-23", "close": 10.71, "volume": 8743400}, {"date": "2025-01-24", "close": 10.91, "volume": 22305800}, {"date": "2025-01-27", "close": 10.99, "volume": 7964000}, {"date": "2025-01-28", "close": 10.9, "volume": 7049400}, {"date": "2025-01-29", "close": 10.93, "volume": 12097100}, {"date": "2025-01-30", "close": 10.82, "volume": 6086600}, {"date": "2025-01-31", "close": 10.72, "volume": 6730700}, {"date": "2025-02-03", "close": 10.57, "volume": 7747900}, {"date": "2025-02-04", "close": 10.76, "volume": 5069800}, {"date": "2025-02-05", "close": 10.68, "volume": 7610000}, {"date": "2025-02-06", "close": 10.68, "volume": 6509000}, {"date": "2025-02-07", "close": 10.47, "volume": 9713800}, {"date": "2025-02-10", "close": 10.39, "volume": 6986900}, {"date": "2025-02-11", "close": 10.41, "volume": 6600800}, {"date": "2025-02-12", "close": 10.48, "volume": 7056800}, {"date": "2025-02-13", "close": 10.65, "volume": 8157300}, {"date": "2025-02-14", "close": 11.13, "volume": 15196900}, {"date": "2025-02-18", "close": 11.14, "volume": 8662300}, {"date": "2025-02-19", "close": 11.27, "volume": 12558300}, {"date": "2025-02-20", "close": 11.3, "volume": 8716500}, {"date": "2025-02-21", "close": 11.32, "volume": 10479100}, {"date": "2025-02-24", "close": 11.5, "volume": 12170900}, {"date": "2025-02-25", "close": 11.33, "volume": 6808500}, {"date": "2025-02-26", "close": 11.05, "volume": 10721000}, {"date": "2025-02-27", "close": 11.07, "volume": 13022700}, {"date": "2025-02-28", "close": 11.19, "volume": 10644800}, {"date": "2025-03-03", "close": 11.14, "volume": 7531500}, {"date": "2025-03-04", "close": 11.31, "volume": 9896800}, {"date": "2025-03-05", "close": 11.34, "volume": 7340600}, {"date": "2025-03-06", "close": 11.59, "volume": 9580300}, {"date": "2025-03-07", "close": 11.96, "volume": 23490100}, {"date": "2025-03-10", "close": 11.82, "volume": 9701200}, {"date": "2025-03-11", "close": 11.3, "volume": 9890300}, {"date": "2025-03-12", "close": 11.41, "volume": 8263300}, {"date": "2025-03-13", "close": 11.47, "volume": 8631100}, {"date": "2025-03-14", "close": 11.52, "volume": 7311000}, {"date": "2025-03-17", "close": 11.56, "volume": 4617800}, {"date": "2025-03-18", "close": 11.54, "volume": 5674500}, {"date": "2025-03-19", "close": 11.62, "volume": 4716900}, {"date": "2025-03-20", "close": 11.8, "volume": 7015300}, {"date": "2025-03-21", "close": 11.73, "volume": 14225600}, {"date": "2025-03-24", "close": 11.52, "volume": 8707200}, {"date": "2025-03-25", "close": 11.49, "volume": 5114600}, {"date": "2025-03-26", "close": 11.73, "volume": 9531000}, {"date": "2025-03-27", "close": 11.56, "volume": 4951500}, {"date": "2025-03-28", "close": 11.44, "volume": 5616800}, {"date": "2025-03-31", "close": 11.83, "volume": 27065100}, {"date": "2025-04-01", "close": 11.61, "volume": 8941400}, {"date": "2025-04-02", "close": 11.77, "volume": 9139800}, {"date": "2025-04-03", "close": 11.36, "volume": 12422900}, {"date": "2025-04-04", "close": 10.95, "volume": 12062000}, {"date": "2025-04-07", "close": 10.74, "volume": 10078500}, {"date": "2025-04-08", "close": 10.54, "volume": 9428100}, {"date": "2025-04-09", "close": 11.02, "volume": 13870800}, {"date": "2025-04-10", "close": 10.8, "volume": 9002300}, {"date": "2025-04-11", "close": 10.58, "volume": 5527900}, {"date": "2025-04-14", "close": 10.58, "volume": 7252100}, {"date": "2025-04-15", "close": 10.74, "volume": 7281300}, {"date": "2025-04-16", "close": 10.6, "volume": 6800400}, {"date": "2025-04-17", "close": 10.82, "volume": 6698700}, {"date": "2025-04-21", "close": 10.65, "volume": 8080100}, {"date": "2025-04-22", "close": 10.86, "volume": 8037700}, {"date": "2025-04-23", "close": 11.08, "volume": 7790600}, {"date": "2025-04-24", "close": 11.31, "volume": 7738800}, {"date": "2025-04-25", "close": 11.61, "volume": 9442400}, {"date": "2025-04-28", "close": 11.57, "volume": 5973300}, {"date": "2025-04-29", "close": 11.62, "volume": 6566200}, {"date": "2025-04-30", "close": 11.62, "volume": 9558900}, {"date": "2025-05-01", "close": 11.53, "volume": 6187900}, {"date": "2025-05-02", "close": 11.31, "volume": 8118200}, {"date": "2025-05-05", "close": 11.13, "volume": 8507100}, {"date": "2025-05-06", "close": 11.38, "volume": 6553000}, {"date": "2025-05-07", "close": 11.45, "volume": 6747000}, {"date": "2025-05-08", "close": 11.56, "volume": 7212600}, {"date": "2025-05-09", "close": 11.81, "volume": 10208500}, {"date": "2025-05-12", "close": 11.82, "volume": 8104900}, {"date": "2025-05-13", "close": 11.86, "volume": 5141100}, {"date": "2025-05-14", "close": 11.68, "volume": 7454300}, {"date": "2025-05-15", "close": 11.77, "volume": 5352400}, {"date": "2025-05-16", "close": 11.58, "volume": 10259000}, {"date": "2025-05-19", "close": 11.65, "volume": 6316300}, {"date": "2025-05-20", "close": 11.74, "volume": 5254000}, {"date": "2025-05-21", "close": 11.76, "volume": 9160700}, {"date": "2025-05-22", "close": 11.73, "volume": 4032000}, {"date": "2025-05-23", "close": 11.84, "volume": 4866700}, {"date": "2025-05-27", "close": 11.9, "volume": 4326400}, {"date": "2025-05-28", "close": 11.96, "volume": 6120100}, {"date": "2025-05-29", "close": 12.05, "volume": 6924400}, {"date": "2025-05-30", "close": 11.97, "volume": 9097500}, {"date": "2025-06-02", "close": 11.81, "volume": 8611900}, {"date": "2025-06-03", "close": 11.88, "volume": 5524700}, {"date": "2025-06-04", "close": 11.8, "volume": 4624700}, {"date": "2025-06-05", "close": 11.77, "volume": 6600700}, {"date": "2025-06-06", "close": 11.79, "volume": 4884400}, {"date": "2025-06-09", "close": 11.87, "volume": 4614200}, {"date": "2025-06-10", "close": 12.04, "volume": 6573900}, {"date": "2025-06-11", "close": 12.11, "volume": 6809900}, {"date": "2025-06-12", "close": 11.81, "volume": 9140400}, {"date": "2025-06-13", "close": 11.76, "volume": 5725100}, {"date": "2025-06-16", "close": 11.91, "volume": 5138800}, {"date": "2025-06-17", "close": 11.89, "volume": 10746300}, {"date": "2025-06-18", "close": 11.96, "volume": 9770900}, {"date": "2025-06-20", "close": 12.27, "volume": 27163800}, {"date": "2025-06-23", "close": 12.24, "volume": 6341000}, {"date": "2025-06-24", "close": 12.13, "volume": 4993100}, {"date": "2025-06-25", "close": 12.14, "volume": 5850400}, {"date": "2025-06-26", "close": 12.24, "volume": 5008500}, {"date": "2025-06-27", "close": 12.45, "volume": 8020200}, {"date": "2025-06-30", "close": 12.82, "volume": 12951100}, {"date": "2025-07-01", "close": 13.07, "volume": 12925600}, {"date": "2025-07-02", "close": 12.76, "volume": 10630400}, {"date": "2025-07-03", "close": 12.82, "volume": 4141400}, {"date": "2025-07-07", "close": 12.45, "volume": 9746000}, {"date": "2025-07-08", "close": 12.55, "volume": 7522800}, {"date": "2025-07-09", "close": 12.53, "volume": 7622500}, {"date": "2025-07-10", "close": 12.69, "volume": 5848900}, {"date": "2025-07-11", "close": 12.67, "volume": 4084500}, {"date": "2025-07-14", "close": 12.92, "volume": 10525400}, {"date": "2025-07-15", "close": 12.88, "volume": 9600400}, {"date": "2025-07-16", "close": 12.89, "volume": 3037200}, {"date": "2025-07-17", "close": 12.86, "volume": 5853100}, {"date": "2025-07-18", "close": 12.91, "volume": 6848200}, {"date": "2025-07-21", "close": 12.95, "volume": 4758000}, {"date": "2025-07-22", "close": 13.03, "volume": 4139600}, {"date": "2025-07-23", "close": 13.11, "volume": 4885900}, {"date": "2025-07-24", "close": 13.17, "volume": 10758000}, {"date": "2025-07-25", "close": 12.97, "volume": 25566700}, {"date": "2025-07-28", "close": 12.96, "volume": 25205600}, {"date": "2025-07-29", "close": 13.16, "volume": 28752100}, {"date": "2025-07-30", "close": 13.21, "volume": 32766300}, {"date": "2025-07-31", "close": 12.49, "volume": 12951500}, {"date": "2025-08-01", "close": 12.93, "volume": 9689900}, {"date": "2025-08-04", "close": 12.23, "volume": 6560500}, {"date": "2025-08-05", "close": 11.67, "volume": 10124100}, {"date": "2025-08-06", "close": 10.97, "volume": 75616700}, {"date": "2025-08-07", "close": 11.66, "volume": 43086700}, {"date": "2025-08-08", "close": 10.44, "volume": 39967400}, {"date": "2025-08-11", "close": 10.05, "volume": 51349500}, {"date": "2025-08-12", "close": 10.9, "volume": 30385100}, {"date": "2025-08-13", "close": 14.9, "volume": 133664900}, {"date": "2025-08-14", "close": 14.29, "volume": 26039900}, {"date": "2025-08-15", "close": 13.63, "volume": 16703500}, {"date": "2025-08-18", "close": 13.41, "volume": 11959400}, {"date": "2025-08-19", "close": 13.39, "volume": 11058900}, {"date": "2025-08-20", "close": 13.89, "volume": 9088500}, {"date": "2025-08-21", "close": 15.93, "volume": 46431500}, {"date": "2025-08-22", "close": 15.9, "volume": 14871600}, {"date": "2025-08-25", "close": 15.86, "volume": 8131600}, {"date": "2025-08-26", "close": 15.74, "volume": 14226800}, {"date": "2025-08-27", "close": 14.71, "volume": 12166100}, {"date": "2025-08-28", "close": 14.59, "volume": 5585000}, {"date": "2025-08-29", "close": 14.6, "volume": 4862800}, {"date": "2025-09-02", "close": 14.37, "volume": 5127200}, {"date": "2025-09-03", "close": 14.96, "volume": 8362700}, {"date": "2025-09-04", "close": 14.64, "volume": 5291800}, {"date": "2025-09-05", "close": 14.9, "volume": 7422200}, {"date": "2025-09-08", "close": 15.09, "volume": 6514800}, {"date": "2025-09-09", "close": 15.1, "volume": 6071100}, {"date": "2025-09-10", "close": 15.01, "volume": 6164300}, {"date": "2025-09-11", "close": 17.35, "volume": 48508800}, {"date": "2025-09-12", "close": 18.67, "volume": 32421300}, {"date": "2025-09-15", "close": 18.51, "volume": 11157400}, {"date": "2025-09-16", "close": 17.46, "volume": 9622700}, {"date": "2025-09-17", "close": 17.85, "volume": 7332400}, {"date": "2025-09-18", "close": 17.81, "volume": 5567000}, {"date": "2025-09-19", "close": 18.85, "volume": 21734800}, {"date": "2025-09-22", "close": 18.54, "volume": 13813100}, {"date": "2025-09-23", "close": 19.65, "volume": 23432200}, {"date": "2025-09-24", "close": 19.05, "volume": 11908400}, {"date": "2025-09-25", "close": 18.86, "volume": 7548200}, {"date": "2025-09-26", "close": 18.85, "volume": 4528900}, {"date": "2025-09-29", "close": 19.43, "volume": 8183600}, {"date": "2025-09-30", "close": 18.85, "volume": 11997100}, {"date": "2025-10-01", "close": 18.82, "volume": 4903000}, {"date": "2025-10-02", "close": 18.55, "volume": 4635400}, {"date": "2025-10-03", "close": 19.02, "volume": 12239000}, {"date": "2025-10-06", "close": 19.06, "volume": 10251200}, {"date": "2025-10-07", "close": 18.44, "volume": 5035200}, {"date": "2025-10-08", "close": 18.43, "volume": 8336300}, {"date": "2025-10-09", "close": 17.9, "volume": 4697900}, {"date": "2025-10-10", "close": 16.94, "volume": 6055600}, {"date": "2025-10-13", "close": 17.03, "volume": 4426700}, {"date": "2025-10-14", "close": 17.22, "volume": 4230800}, {"date": "2025-10-15", "close": 17.36, "volume": 3790100}, {"date": "2025-10-16", "close": 16.84, "volume": 4354500}, {"date": "2025-10-17", "close": 16.71, "volume": 4216200}, {"date": "2025-10-20", "close": 16.93, "volume": 2422000}, {"date": "2025-10-21", "close": 16.45, "volume": 4350700}, {"date": "2025-10-22", "close": 16.51, "volume": 2655200}, {"date": "2025-10-23", "close": 16.41, "volume": 3585500}, {"date": "2025-10-24", "close": 16.66, "volume": 2239000}, {"date": "2025-10-27", "close": 16.51, "volume": 3798300}, {"date": "2025-10-28", "close": 16.15, "volume": 3481800}, {"date": "2025-10-29", "close": 15.82, "volume": 4414400}, {"date": "2025-10-30", "close": 15.4, "volume": 4880200}, {"date": "2025-10-31", "close": 15.33, "volume": 6730500}, {"date": "2025-11-03", "close": 15.36, "volume": 6608200}, {"date": "2025-11-04", "close": 14.78, "volume": 7350400}, {"date": "2025-11-05", "close": 15.03, "volume": 6114600}, {"date": "2025-11-06", "close": 14.74, "volume": 6506000}, {"date": "2025-11-07", "close": 15.04, "volume": 9772900}, {"date": "2025-11-10", "close": 15.19, "volume": 13006300}, {"date": "2025-11-11", "close": 16.68, "volume": 15858700}, {"date": "2025-11-12", "close": 15.51, "volume": 12218000}, {"date": "2025-11-13", "close": 15.31, "volume": 5957600}, {"date": "2025-11-14", "close": 15.62, "volume": 6226900}, {"date": "2025-11-17", "close": 15.67, "volume": 7821900}, {"date": "2025-11-18", "close": 16.03, "volume": 10117500}, {"date": "2025-11-19", "close": 15.41, "volume": 7942600}, {"date": "2025-11-20", "close": 15.62, "volume": 8946300}, {"date": "2025-11-21", "close": 15.83, "volume": 5483100}, {"date": "2025-11-24", "close": 15.0, "volume": 13558300}, {"date": "2025-11-25", "close": 15.58, "volume": 4552500}, {"date": "2025-11-26", "close": 15.73, "volume": 6666200}, {"date": "2025-11-28", "close": 15.96, "volume": 2774900}, {"date": "2025-12-01", "close": 15.65, "volume": 4571600}, {"date": "2025-12-02", "close": 15.76, "volume": 6446300}, {"date": "2025-12-03", "close": 14.61, "volume": 9614700}, {"date": "2025-12-04", "close": 14.76, "volume": 7527200}, {"date": "2025-12-05", "close": 13.32, "volume": 27103900}, {"date": "2025-12-08", "close": 14.51, "volume": 39522900}, {"date": "2025-12-09", "close": 14.58, "volume": 15404800}, {"date": "2025-12-10", "close": 14.66, "volume": 14626200}, {"date": "2025-12-11", "close": 14.07, "volume": 19132600}, {"date": "2025-12-12", "close": 13.69, "volume": 10241500}, {"date": "2025-12-15", "close": 13.94, "volume": 6609300}, {"date": "2025-12-16", "close": 13.8, "volume": 7513000}, {"date": "2025-12-17", "close": 13.05, "volume": 12883200}, {"date": "2025-12-18", "close": 13.01, "volume": 7405300}, {"date": "2025-12-19", "close": 13.05, "volume": 23333000}, {"date": "2025-12-22", "close": 13.61, "volume": 11618000}, {"date": "2025-12-23", "close": 13.53, "volume": 4407500}, {"date": "2025-12-24", "close": 13.74, "volume": 2464100}, {"date": "2025-12-26", "close": 13.59, "volume": 2886800}, {"date": "2025-12-29", "close": 13.5, "volume": 4764400}, {"date": "2025-12-30", "close": 13.51, "volume": 3937200}, {"date": "2025-12-31", "close": 13.4, "volume": 5084300}, {"date": "2026-01-02", "close": 13.18, "volume": 5927700}, {"date": "2026-01-05", "close": 12.98, "volume": 7570600}, {"date": "2026-01-06", "close": 12.5, "volume": 11137900}, {"date": "2026-01-07", "close": 12.37, "volume": 6702800}, {"date": "2026-01-08", "close": 12.27, "volume": 7859300}, {"date": "2026-01-09", "close": 12.06, "volume": 7700100}, {"date": "2026-01-12", "close": 12.15, "volume": 6919800}, {"date": "2026-01-13", "close": 12.14, "volume": 7364500}, {"date": "2026-01-14", "close": 12.08, "volume": 4829700}, {"date": "2026-01-15", "close": 11.83, "volume": 6835800}, {"date": "2026-01-16", "close": 11.8, "volume": 6144200}, {"date": "2026-01-20", "close": 11.55, "volume": 11269900}, {"date": "2026-01-21", "close": 11.6, "volume": 5892500}, {"date": "2026-01-22", "close": 11.78, "volume": 7224800}, {"date": "2026-01-23", "close": 11.7, "volume": 4484100}, {"date": "2026-01-26", "close": 11.89, "volume": 6274200}, {"date": "2026-01-27", "close": 11.55, "volume": 5415900}, {"date": "2026-01-28", "close": 11.34, "volume": 4473300}, {"date": "2026-01-29", "close": 11.26, "volume": 7729500}, {"date": "2026-01-30", "close": 11.21, "volume": 5749900}]}}